mardor/__init__.py
mardor/cli.py
mardor/format.py
mardor/mozilla.py
mardor/reader.py
mardor/signing.py
mardor/utils.py
mardor/writer.py
mar-3.2.0.dist-info/AUTHORS.rst
mar-3.2.0.dist-info/LICENSE
mar-3.2.0.dist-info/METADATA
mar-3.2.0.dist-info/WHEEL
mar-3.2.0.dist-info/entry_points.txt
mar-3.2.0.dist-info/top_level.txt
mar-3.2.0.dist-info/RECORD
