Metadata-Version: 2.1
Name: mar
Version: 3.2.0
Summary: Package for handling Mozilla Archive files.
Home-page: https://github.com/mozilla-releng/build-mar
Author: Chris AtLee
Author-email: catlee@mozilla.com
License: MPL 2.0
Keywords: mozilla,mar,archive
Platform: UNKNOWN
Classifier: Development Status :: 5 - Production/Stable
Classifier: Intended Audience :: Developers
Classifier: License :: OSI Approved :: Mozilla Public License 2.0 (MPL 2.0)
Classifier: Operating System :: Unix
Classifier: Operating System :: POSIX
Classifier: Operating System :: Microsoft :: Windows
Classifier: Programming Language :: Python
Classifier: Programming Language :: Python :: 2.7
Classifier: Programming Language :: Python :: 3
Classifier: Programming Language :: Python :: 3.7
Classifier: Programming Language :: Python :: 3.8
Classifier: Programming Language :: Python :: 3.9
Classifier: Programming Language :: Python :: 3.10
Classifier: Programming Language :: Python :: Implementation :: CPython
Classifier: Programming Language :: Python :: Implementation :: PyPy
Classifier: Topic :: Utilities
License-File: LICENSE
License-File: AUTHORS.rst
Requires-Dist: asn1crypto
Requires-Dist: click
Requires-Dist: construct
Requires-Dist: cryptography
Requires-Dist: six
